src/__init__.py
src/commands/__init__.py
src/commands/backups/__init__.py
src/commands/backups/create.py
src/commands/backups/raw/__init__.py
src/commands/backups/raw/create.py
src/commands/backups/raw/download.py
src/commands/backups/raw/list.py
src/commands/backups/raw/restore.py
src/commands/backups/restore.py
src/commands/down.py
src/commands/log.py
src/commands/restart.py
src/commands/status.py
src/commands/up.py
src/main.py
src/utils/__init__.py
src/utils/backup.py
src/utils/backup_rich.py
src/utils/bbak.py
src/utils/cli.py
src/utils/common.py
src/utils/completers.py
src/utils/completers_autocompletion.py
src/utils/compose.py
src/utils/compose_rich.py
src/utils/console.py
src/utils/doco.py
src/utils/doco_config.py
src/utils/exceptions_rich.py
src/utils/restore.py
src/utils/restore_rich.py
src/utils/rich.py
src/utils/rsync.py
src/utils/system.py
src/utils/validators.py
doco_cli-2.2.2.dist-info/LICENSE
doco_cli-2.2.2.dist-info/METADATA
doco_cli-2.2.2.dist-info/WHEEL
doco_cli-2.2.2.dist-info/entry_points.txt
doco_cli-2.2.2.dist-info/RECORD
