Metadata-Version: 2.1
Name: doco-cli
Version: 2.2.2
Summary: 
Home-page: https://github.com/bibermann/doco-cli
License: GPL-3.0-only
Keywords: docker,rsync
Author: Fabian Sandoval Saldias
Author-email: fabianvss@gmail.com
Requires-Python: >=3.9.2,<4.0.0
Classifier: License :: OSI Approved :: GNU General Public License v3 (GPLv3)
Classifier: Programming Language :: Python :: 3
Classifier: Programming Language :: Python :: 3.10
Classifier: Programming Language :: Python :: 3.11
Classifier: Programming Language :: Python :: 3.12
Requires-Dist: PyYAML (>=6.0,<7.0)
Requires-Dist: click (==8.0.4)
Requires-Dist: pydantic (>=1.10.2,<2.0.0)
Requires-Dist: python-dotenv (>=0.21.0,<0.22.0)
Requires-Dist: rich (>=12.6.0,<13.0.0)
Requires-Dist: tomli (>=2.0.1,<3.0.0)
Requires-Dist: typer[all] (>=0.6.1,<0.7.0)
Project-URL: Repository, https://github.com/bibermann/doco-cli
